jomfish/__init__.py
jomfish/main.py
jomfish/bin/jomfish
jomfish_linux-0.10.0.dist-info/METADATA
jomfish_linux-0.10.0.dist-info/WHEEL
jomfish_linux-0.10.0.dist-info/entry_points.txt
jomfish_linux-0.10.0.dist-info/top_level.txt
jomfish_linux-0.10.0.dist-info/RECORD
