Metadata-Version: 2.4
Name: jomfish-linux
Version: 0.10.0
Summary: Jomfish - A high-performance chess engine
Author: Jimmy Luong
Author-email: nguyenhungjimmy.luong@gmail.com
Classifier: Programming Language :: Python :: 3
Classifier: License :: OSI Approved :: MIT License
Classifier: Operating System :: POSIX :: Linux
Requires-Python: >=3.6
Dynamic: author
Dynamic: author-email
Dynamic: classifier
Dynamic: requires-python
Dynamic: summary
